{
  "$schema": "https://ui.shadcn.com/schema/registry-item.json",
  "name": "breadcrumb-02",
  "type": "registry:component",
  "registryDependencies": [],
  "files": [
    {
      "path": "registry/default/components/breadcrumb/breadcrumb-02.tsx",
      "content": "\nimport {\n  Breadcrumb, \n  BreadcrumbItem,\n  BreadcrumbLink,\n  BreadcrumbList,\n  BreadcrumbPage,\n  BreadcrumbSeparator,\n} from \"@/registry/default/ui/breadcrumb\"\nimport { Slash } from \"lucide-react\"\nimport Link from \"next/link\"\n\nexport default function Component() {\n  return (\n    <div>\n     <Breadcrumb>\n      <BreadcrumbList>\n        <BreadcrumbItem>\n          <BreadcrumbLink asChild>\n            <Link href=\"#\">Home</Link>\n          </BreadcrumbLink>\n        </BreadcrumbItem>\n        <BreadcrumbSeparator>\n          <Slash className=\"w-4 h-4\"/>\n        </BreadcrumbSeparator>\n        <BreadcrumbItem>\n          <BreadcrumbLink asChild>\n            <Link href=\"#\">Fonts</Link>\n          </BreadcrumbLink>\n        </BreadcrumbItem>\n        <BreadcrumbSeparator>\n            <Slash className=\"w-4 h-4\"/>\n        </BreadcrumbSeparator>\n        <BreadcrumbItem>\n          <BreadcrumbPage>Breadcrumb</BreadcrumbPage>\n        </BreadcrumbItem>\n      </BreadcrumbList>\n    </Breadcrumb>\n    </div>\n  )\n}\n",
      "type": "registry:component"
    }
  ],
  "meta": {
    "tags": [
      "breadcrumb",
      "example",
      "component"
    ],
    "style": 1,
    "colSpan": 2
  }
}